pywifi/__init__.py
pywifi/_wifiutil_linux.py
pywifi/_wifiutil_win.py
pywifi/const.py
pywifi/iface.py
pywifi/profile.py
pywifi/wifi.py
tests/__init__.py
tests/pywifi_test.py
pywifi-1.1.12.dist-info/LICENSE
pywifi-1.1.12.dist-info/METADATA
pywifi-1.1.12.dist-info/WHEEL
pywifi-1.1.12.dist-info/top_level.txt
pywifi-1.1.12.dist-info/RECORD
