Metadata-Version: 2.1
Name: pywifi
Version: 1.1.12
Summary: A cross-platform module for manipulating WiFi devices.
Home-page: https://github.com/awkman/pywifi
Author: Jiang Sheng-Jhih
Author-email: shengjhih@gmail.com
License: MIT
Download-URL: https://github.com/awkman/pywifi/archive/master.zip
Keywords: wifi,wireless,Linux,Windows
Platform: UNKNOWN
Classifier: Intended Audience :: Developers
Classifier: Topic :: Utilities
Classifier: License :: OSI Approved :: MIT License
Classifier: Programming Language :: Python :: 2.7
Classifier: Programming Language :: Python :: 3.4
Classifier: Programming Language :: Python :: 3.5
Classifier: Programming Language :: Python :: 3.6
Classifier: Programming Language :: Python :: 3.7
Requires-Python: >=2.7, !=3.0.*, !=3.1.*, !=3.2.*, !=3.3.*
